MANIFEST.in
readme.rst
setup.py
tinyble/Collection.py
tinyble/JSONStorage.py
tinyble/LRU.py
tinyble/__init__.py
tinyble/query.py
tinyble/tinyble.py
tinyble/utils.py
tinyble.egg-info/PKG-INFO
tinyble.egg-info/SOURCES.txt
tinyble.egg-info/dependency_links.txt
tinyble.egg-info/not-zip-safe
tinyble.egg-info/top_level.txt