Metadata-Version: 1.0
Name: tinyble
Version: 0.1.4.2
Summary: A tiny NoSQL database with in-memory caching
Home-page: https://github.com/StevenSLXie/tinyble
Author: Steven S.L. Xie
Author-email: stevenslxie@gmail.com
License: MIT
Platform: UNKNOWN
